LICENSE
MANIFEST.in
README.md
requirements.txt
setup.py
version.txt
cf_api/__init__.py
cf_api/__version__.py
cf_api/deploy_blue_green.py
cf_api/deploy_manifest.py
cf_api/deploy_service.py
cf_api/deploy_space.py
cf_api/dropsonde_util.py
cf_api/exceptions.py
cf_api/logs_util.py
cf_api/pb2dict.py
cf_api/routes_util.py
cf_api/ssh_util.py
cf_api.egg-info/PKG-INFO
cf_api.egg-info/SOURCES.txt
cf_api.egg-info/dependency_links.txt
cf_api.egg-info/requires.txt
cf_api.egg-info/top_level.txt
test/test_all.py
test/test_cf_api.py