Metadata-Version: 2.1
Name: cf-api
Version: 1.0.0
Summary: Python Interface for Cloud Foundry APIs
Home-page: https://github.com/hsdp/python-cf-api
Author: Adam Jaso
Author-email: ajaso@hsdp.io
License: Apache License Version 2.0
Platform: UNKNOWN
